{
  "known_mods": {
    "common": [
      {
        "name": "HiFi DLC",
        "url": "https://nyrds.github.io/NYRDS/common/HiFiDLC.rpd",
        "version": 2,
        "rpdVersion": 964
      },
      {
        "name": "Faith",
        "url": "https://nyrds.github.io/NYRDS/common/Faith_v5.zip",
        "version": 6,
        "rpdVersion": 610
      },
      {
        "name": "Remixed Additions",
        "url": "https://nyrds.github.io/NYRDS/common/Remixed_Additions.zip",
        "version": 17,
        "rpdVersion": 1006
      },
      {
        "name": "Remixed RPG",
        "url": "https://nyrds.net/rpd/mods/Remixed_RPG_v25.zip",
        "version": 25,
        "rpdVersion":  1056
      },
      {
        "name": "The epic dungeon",
        "url": "https://nyrds.net/rpd/mods/The_epic_dungeon_v_30.zip",
        "version": 30,
        "rpdVersion":  1054
      },
      {
        "name": "Maze",
        "url": "https://nyrds.github.io/NYRDS/common/Maze.zip",
        "version": 24,
        "rpdVersion": 599
      },
      {
        "name": "PD Mini",
        "url": "https://nyrds.github.io/NYRDS/common/PD_mini.zip",
        "version": 15,
        "rpdVersion": 0
      },
      {
        "name": "PD Vanilla",
        "url": "https://nyrds.github.io/NYRDS/common/PD_Vanilla.zip",
        "version": 11,
        "rpdVersion": 0
      }
    ],
    "ru": [
      {
        "name": "D.U.N.G.E.O.N",
        "url": "https://nyrds.github.io/NYRDS/ru/D.U.N.G.E.O.N.zip",
        "version": 8,
        "rpdVersion": 929
      },
      {
        "name": "Conundrum",
        "url": "https://nyrds.github.io/NYRDS/ru/Conundrum.zip",
        "version": 24,
        "rpdVersion": 568
      },
      {
        "name": "The Dungeon of Heroes",
        "url": "https://nyrds.github.io/NYRDS/ru/The-dungeon-of-heroes_v2.zip",
        "version": 2,
        "rpdVersion": 610
      }
    ]
  }
}
